output/wait-example-v0.sv
module DUT_sc_module_0 (
);
  logic signed[63:0] double_sig;
  logic signed[31:0] sig1;
  logic signed[31:0] others;
  test_sc_module_1 testing(
    .in1(sig1),
    .out1(sig1)
  );
  always @(*) begin
  end

endmodule
module test_sc_module_1 (
  input logic [0:0] clk,
  input logic signed[31:0] in1,
  input logic [0:0] reset,
  output logic signed[31:0] out1
);
  logic signed[31:0] k;
  logic signed[31:0] _scclang_state_single_wait;
  logic signed[31:0] _scclang_next_state_single_wait;
  logic signed[31:0] _scclang_wait_counter_single_wait;
  logic signed[31:0] _scclang_next_wait_counter_single_wait;
  logic signed[31:0] _scclang_wait_next_state_single_wait;
  logic signed[31:0] _scclang_save_wait_next_state_single_wait;
  // Thread: single_wait
  always @(posedge clk or negedge reset) begin: single_wait_state_update
    if ((reset) == (0)) begin
      _scclang_state_single_wait <= (0);
      _scclang_wait_next_state_single_wait <= (0);
      _scclang_wait_counter_single_wait <= (0);
    end else begin
      _scclang_state_single_wait <= (_scclang_next_state_single_wait);
      _scclang_wait_counter_single_wait <= (_scclang_next_wait_counter_single_wait);
      _scclang_wait_next_state_single_wait <= (_scclang_save_wait_next_state_single_wait);
    end

  end
  always @(*) begin: single_wait
    // default case to prevent Latch generation
    // we might need generate default assignments for all signals written in
    // single_wait
    _scclang_next_state_single_wait =  _scclang_state_single_wait;
    _scclang_next_wait_counter_single_wait = _scclang_wait_counter_single_wait;
    _scclang_save_wait_next_state_single_wait = _scclang_wait_next_state_single_wait;
    case(_scclang_state_single_wait)
      0: begin
        if (1) begin
          k = 1;
          _scclang_next_wait_counter_single_wait = 4;
          _scclang_save_wait_next_state_single_wait = 1;
          _scclang_next_state_single_wait = 2;
        end
      end
      1: begin
        k = 2;
        if (1) begin
          k = 1;
          _scclang_next_wait_counter_single_wait = 4;
          _scclang_save_wait_next_state_single_wait = 1;
          _scclang_next_state_single_wait = 2;
        end
      end
      2: begin
        // an alternative
        // _scclang_next_wait_counter_single_wait = _scclang_wait_counter_single_wait - 1;
        _scclang_next_wait_counter_single_wait--;
        if ((_scclang_next_wait_counter_single_wait) == (0)) begin
          _scclang_next_state_single_wait = _scclang_wait_next_state_single_wait;
        end
      end
    endcase
  end
endmodule

tb.sv
module tb;
  logic clock = 0;
  logic arst;
  initial forever begin
    clock = #5 !clock;
  end
  initial begin
    arst = 1;
    #10; 
    arst = 0;
    #10;
    arst = 1;
    #150;
    $finish;
  end
  initial begin
    $dumpfile("single-wait.vcd");
    $dumpvars;
  end
  test_sc_module_1 dut(
    .clk(clock),
    .reset(arst)
  );
endmodule

single-wait.vcd
$date
	Wed Oct 13 16:08:17 2021
$end
$version
	Icarus Verilog
$end
$timescale
	1s
$end
$scope module tb $end
$var reg 1 ! arst $end
$var reg 1 " clock $end
$scope module dut $end
$var wire 1 " clk $end
$var wire 32 # in1 [31:0] $end
$var wire 1 ! reset $end
$var reg 32 $ _scclang_next_state_single_wait [31:0] $end
$var reg 32 % _scclang_next_wait_counter_single_wait [31:0] $end
$var reg 32 & _scclang_save_wait_next_state_single_wait [31:0] $end
$var reg 32 ' _scclang_state_single_wait [31:0] $end
$var reg 32 ( _scclang_wait_counter_single_wait [31:0] $end
$var reg 32 ) _scclang_wait_next_state_single_wait [31:0] $end
$var reg 32 * k [31:0] $end
$var reg 32 + out1 [31:0] $end
$scope begin single_wait $end
$upscope $end
$scope begin single_wait_state_update $end
$upscope $end
$upscope $end
$upscope $end
$enddefinitions $end
#0
$dumpvars
bx +
bx *
bx )
bx (
bx '
bx &
bx %
bx $
bz #
0"
1!
$end
#5
1"
#10
b1 *
b1 &
b100 %
b10 $
b0 (
b0 )
b0 '
0"
0!
#15
1"
#20
0"
1!
#25
b11 %
b1 )
b100 (
b10 '
1"
#30
0"
#35
b10 %
b11 (
1"
#40
0"
#45
b1 %
b10 (
1"
#50
0"
#55
b1 $
b0 %
b1 (
1"
#60
0"
#65
b10 $
b100 %
b1 *
b0 (
b1 '
1"
#70
0"
#75
b11 %
b100 (
b10 '
1"
#80
0"
#85
b10 %
b11 (
1"
#90
0"
#95
b1 %
b10 (
1"
#100
0"
#105
b1 $
b0 %
b1 (
1"
#110
0"
#115
b10 $
b100 %
b1 *
b0 (
b1 '
1"
#120
0"
#125
b11 %
b100 (
b10 '
1"
#130
0"
#135
b10 %
b11 (
1"
#140
0"
#145
b1 %
b10 (
1"
#150
0"
#155
b1 $
b0 %
b1 (
1"
#160
0"
#165
b10 $
b100 %
b1 *
b0 (
b1 '
1"
